pygc/__init__.py
pygc/_version.py
pygc/gc.py
pygc/tests/__init__.py
pygc/tests/test_gc.py
pygc/tests/test_gd.py
pygc/tests/x.npy
pygc/tests/xmask.npy
pygc/tests/y.npy
pygc/tests/ymask.npy
pygc-2.0.0.dist-info/LICENSE
pygc-2.0.0.dist-info/METADATA
pygc-2.0.0.dist-info/WHEEL
pygc-2.0.0.dist-info/top_level.txt
pygc-2.0.0.dist-info/zip-safe
pygc-2.0.0.dist-info/RECORD
